gitspindle/__init__.py
gitspindle/ansi.py
gitspindle/bbapi.py
gitspindle/bitbucket.py
gitspindle/github.py
gitspindle/gitlab.py
gitspindle/monkey.py
gitspindle/public_suffix.py
git_spindle-4.0.1.dist-info/COPYING
git_spindle-4.0.1.dist-info/METADATA
git_spindle-4.0.1.dist-info/WHEEL
git_spindle-4.0.1.dist-info/entry_points.txt
git_spindle-4.0.1.dist-info/top_level.txt
git_spindle-4.0.1.dist-info/RECORD
